bicleaner/__init__.py
bicleaner/bicleaner_classifier_full.py
bicleaner/bicleaner_classifier_lite.py
bicleaner/bicleaner_download.py
bicleaner/bicleaner_train.py
bicleaner/classify.py
bicleaner/features.py
bicleaner/prob_dict.py
bicleaner/tokenizer.py
bicleaner/training.py
bicleaner/util.py
bicleaner/word_freqs_list.py
bicleaner/word_freqs_zipf.py
bicleaner/word_freqs_zipf_double_linked.py
bicleaner-0.17.4.dist-info/LICENSE
bicleaner-0.17.4.dist-info/METADATA
bicleaner-0.17.4.dist-info/WHEEL
bicleaner-0.17.4.dist-info/entry_points.txt
bicleaner-0.17.4.dist-info/top_level.txt
bicleaner-0.17.4.dist-info/RECORD
