Metadata-Version: 2.1
Name: bicleaner
Version: 0.17.4
Summary: Parallel corpus classifier, indicating the likelihood of a pair of sentences being mutual translations or not
Author-email: Prompsit Language Engineering <info@prompsit.com>
Maintainer-email: Marta Bañón <mbanon@prompsit.com>, Jaume Zaragoza <jzaragoza@prompsit.com>, Tudor Nicolae Mateiu <tudornm@prompsit.com>
License: GNU General Public License v3.0
Project-URL: Homepage, https://github.com/bitextor/bicleaner
Project-URL: Bicleaner on GitHub, https://github.com/bitextor/bicleaner
Project-URL: Prompsit Language Engineering, http://www.prompsit.com
Project-URL: Bicrawler & Bicleaner, https://bicrawler.com
Project-URL: Paracrawl, https://paracrawl.eu/
Classifier: Environment :: Console
Classifier: Intended Audience :: Science/Research
Classifier: Programming Language :: Python :: 3.8
Classifier: License :: OSI Approved :: GNU General Public License v3 (GPLv3)
Classifier: Operating System :: POSIX :: Linux
Classifier: Topic :: Scientific/Engineering :: Artificial Intelligence
Classifier: Topic :: Text Processing :: Linguistic
Classifier: Topic :: Software Development :: Libraries :: Python Modules
Classifier: Topic :: Text Processing :: Filters
Requires-Python: >=3.8
License-File: LICENSE
Requires-Dist: regex
Requires-Dist: scikit-learn ==1.1.3
Requires-Dist: PyYAML
Requires-Dist: numpy
Requires-Dist: scipy >=1.5.4
Requires-Dist: pytest
Requires-Dist: pycld2 ==0.41
Requires-Dist: toolwrapper <=2.1.0,>=0.4.1
Requires-Dist: joblib
Requires-Dist: sacremoses ==0.0.53
Requires-Dist: bicleaner-hardrules ==2.10.3
